xj_location/__init__.py
xj_location/admin.py
xj_location/apps.py
xj_location/config.py
xj_location/models.py
xj_location/urls.py
xj_location/validate.py
xj_location/view.py
xj_location/apis/__init__.py
xj_location/apis/boundary_api.py
xj_location/apis/group_api.py
xj_location/apis/location_api.py
xj_location/services/__init__.py
xj_location/services/boundary_service.py
xj_location/services/location_group_services.py
xj_location/services/location_service.py
xj_location/utils/__init__.py
xj_location/utils/custom_authentication_wrapper.py
xj_location/utils/custom_authorization.py
xj_location/utils/custom_exception.py
xj_location/utils/custom_pagination.py
xj_location/utils/custom_response.py
xj_location/utils/custom_tool.py
xj_location/utils/j_dict.py
xj_location/utils/join_list.py
xj_location/utils/model_handle.py
xj_location/utils/util.py
xj_location/utils/validate.py
xj_location-1.1.8.dist-info/METADATA
xj_location-1.1.8.dist-info/WHEEL
xj_location-1.1.8.dist-info/top_level.txt
xj_location-1.1.8.dist-info/RECORD
