Metadata-Version: 2.1
Name: xj-location
Version: 1.1.8
Summary: 定位模块
Home-page: UNKNOWN
Author: 赵向明
Author-email: sieyoo@163.com
Maintainer: 孙楷炎
Maintainer-email: sky4834@163.com
License: apache 3.0
Platform: UNKNOWN
